MANIFEST.in
requirements.txt
setup.py
django_magnum.egg-info/PKG-INFO
django_magnum.egg-info/SOURCES.txt
django_magnum.egg-info/dependency_links.txt
django_magnum.egg-info/requires.txt
django_magnum.egg-info/top_level.txt
magnum/__init__.py
magnum/package_index.py
magnum/urls.py
magnum/views.py
magnum/serverproject/__init__.py
magnum/serverproject/manage.py
magnum/serverproject/settings.py
magnum/serverproject/urls.py
magnum/templates/magnum/base.html
magnum/templates/magnum/index.html
magnum/templates/magnum/package.html