Metadata-Version: 1.0
Name: django-magnum
Version: 0.1
Summary: An on-demand PyPI cache. Can also serve non-PyPI packages from a local directory.
Home-page: UNKNOWN
Author: Nathan Reynolds
Author-email: nath@nreynolds.me.uk
License: UNKNOWN
Platform: UNKNOWN
